{
  "id": "OnSolve-cf02679dd8cf452ea4be231ae03bd070",
  "event_code": "RWT",
  "eas_text": "A CIVIL AUTHORITY HAS ISSUED A REQUIRED WEEKLY TEST FOR THE FOLLOWING COUNTIES/AREAS: Dodge, MN; AT 11:11 AM ON OCT 29, 2025 EFFECTIVE UNTIL 12:11 PM. MESSAGE FROM WSLF/CAP.",
  "extra_text": "This is a required weekly test.  This is only a test.  Dodge County MN.",
  "sent_utc": "2025-10-29T18:11:32+00:00",
  "audio_url": "https://showlowfinityharvester.github.io/ipawscap-archive/alerts/2025/10/29/OnSolve-cf02679dd8cf452ea4be231ae03bd070.mp3"
}