{
  "id": "OnSolve-ed3d2cb4157e41ef9dfa1adc05e0f9ae",
  "event_code": "RWT",
  "eas_text": "A civil authority has issued A REQUIRED WEEKLY TEST for the following counties or areas: Todd, MN; at 7:49 AM on FEB 27, 2019 Effective until 8:49 AM. Message from WSLF/CAP.",
  "extra_text": "This is a test.  This is the Todd County Required Weekly Test.",
  "sent_utc": "2019-02-27T14:49:29+00:00",
  "audio_url": "https://showlowfinityharvester.github.io/ipawscap-archive/alerts/2019/02/27/OnSolve-ed3d2cb4157e41ef9dfa1adc05e0f9ae.mp3"
}