{
  "id": "201255.5b4cce51f2d804c30b51b06d2f4b2f",
  "event_code": "SPW",
  "eas_text": "A civil authority has issued A SHELTER IN PLACE WARNING for the following counties or areas: Montcalm, MI; at 07:16 PM ON APR 14, 2026 Effective until 08:16 PM. Message from WSLF/CAP.",
  "extra_text": "MONTCALM CO IS IN A TORNARDO WARNING UNTIL 10:45PM",
  "sent_utc": "2026-04-15T02:16:51+00:00",
  "audio_url": "https://showlowfinityharvester.github.io/ipawscap-archive/alerts/2026/04/14/201255.5b4cce51f2d804c30b51b06d2f4b2f.mp3"
}