{
  "id": "ASHERGROUP-1728830-post-1782935787",
  "event_code": "RWT",
  "eas_text": "A civil authority has issued A REQUIRED WEEKLY TEST for the following counties or areas: Wright, MN; at 12:56 PM on JUL 1, 2026 Effective until 2:56 PM. Message from WSLF/CAP.",
  "extra_text": "this is the required weekly test for IPAWS for Sherburne County    no action is needed",
  "sent_utc": "2026-07-01T19:56:27+00:00",
  "audio_url": "https://showlowfinityharvester.github.io/ipawscap-archive/alerts/2026/07/01/ASHERGROUP-1728830-post-1782935787.mp3"
}