{
  "alerts": [
    {
      "id": "AK.011_336_2025-10-30T01:02:20-08:00",
      "event_code": "RWT",
      "sent_utc": "2025-10-30T09:02:20+00:00",
      "href": "AK.011_336_2025-10-30T01_02_20-08_00.json"
    },
    {
      "id": "ASHERGROUP-1626663-post-1761829368",
      "event_code": "RWT",
      "sent_utc": "2025-10-30T13:02:48+00:00",
      "href": "ASHERGROUP-1626663-post-1761829368.json"
    },
    {
      "id": "OnSolve-ef8ba2c84bcb4f0fb5532a346f5c2e25",
      "event_code": "RWT",
      "sent_utc": "2025-10-30T14:52:04+00:00",
      "href": "OnSolve-ef8ba2c84bcb4f0fb5532a346f5c2e25.json"
    },
    {
      "id": "2230532746263120",
      "event_code": "RWT",
      "sent_utc": "2025-10-30T15:00:00+00:00",
      "href": "2230532746263120.json"
    },
    {
      "id": "OnSolve-b98b6e17719f4960862ea55c7710deb3",
      "event_code": "RWT",
      "sent_utc": "2025-10-30T15:07:53+00:00",
      "href": "OnSolve-b98b6e17719f4960862ea55c7710deb3.json"
    },
    {
      "id": "AS-ID-55d5086e-d222-4b98-837c-3bbb1e46e1fc",
      "event_code": "RWT",
      "sent_utc": "2025-10-30T15:14:37+00:00",
      "href": "AS-ID-55d5086e-d222-4b98-837c-3bbb1e46e1fc.json"
    },
    {
      "id": "2230567105998686",
      "event_code": "RWT",
      "sent_utc": "2025-10-30T15:29:55+00:00",
      "href": "2230567105998686.json"
    },
    {
      "id": "OnSolve-a2127381394e4a87a5350bde9aefcb29",
      "event_code": "BLU",
      "sent_utc": "2025-10-30T15:38:23+00:00",
      "href": "OnSolve-a2127381394e4a87a5350bde9aefcb29.json"
    },
    {
      "id": "b1dbb71ca00a418aacde01ca051b40",
      "event_code": "RWT",
      "sent_utc": "2025-10-30T16:47:38+00:00",
      "href": "b1dbb71ca00a418aacde01ca051b40.json"
    },
    {
      "id": "OnSolve-3f2e069a85324dccab3bfa8fbc66d232",
      "event_code": "RWT",
      "sent_utc": "2025-10-30T16:59:59+00:00",
      "href": "OnSolve-3f2e069a85324dccab3bfa8fbc66d232.json"
    }
  ]
}