{
  "id": "2178855700016898",
  "event_code": "RWT",
  "eas_text": "A CIVIL AUTHORITY HAS ISSUED A REQUIRED WEEKLY TEST FOR THE FOLLOWING COUNTIES/AREAS: New Jersey; AT 07:01 AM ON OCT 09, 2025 EFFECTIVE UNTIL 09:01 AM. MESSAGE FROM WSLF/CAP.",
  "extra_text": "The New Jersey Office of Emergency Management is conducting a test of the Emergency Alert System.  Had this been an actual emergency, the attention signal you have just heard would have been followed by official information or instructions.  This concludes the test of the Emergency Alert System.",
  "sent_utc": "2025-10-09T14:01:50+00:00",
  "audio_url": "https://showlowfinityharvester.github.io/ipawscap-archive/alerts/2025/10/09/2178855700016898.mp3"
}