{
  "id": "2269462329822290",
  "event_code": "RWT",
  "eas_text": "A CIVIL AUTHORITY HAS ISSUED A REQUIRED WEEKLY TEST FOR THE FOLLOWING COUNTIES/AREAS: Clay, MN; Cass, ND; AT 09:11 AM ON NOV 23, 2025 EFFECTIVE UNTIL 10:11 AM. MESSAGE FROM WSLF/CAP.",
  "extra_text": "This is a Required Weekly Test. This is only a test. Red River Regional Dispatch Center.",
  "sent_utc": "2025-11-23T16:11:10+00:00",
  "audio_url": "https://showlowfinityharvester.github.io/ipawscap-archive/alerts/2025/11/23/2269462329822290.mp3"
}