{
  "id": "2336704337919272",
  "event_code": "RMT",
  "eas_text": "A civil authority has issued A REQUIRED MONTHLY TEST for the following counties or areas: Virginia; at 10:45 PM ON FEB 9, 2026 Effective until 12:45 AM FEB 10, 2026. Message from WSLF/CAP.",
  "extra_text": "This is a test of the Virginia Emergency Alert system. In the event of an emergency, this system would bring you important information.",
  "sent_utc": "2026-02-10T05:45:30+00:00",
  "audio_url": "https://showlowfinityharvester.github.io/ipawscap-archive/alerts/2026/02/09/2336704337919272.mp3"
}