{
  "alerts": [
    {
      "id": "2345603510111239",
      "event_code": "RWT",
      "sent_utc": "2026-02-17T07:00:15+00:00",
      "href": "2345603510111239.json"
    },
    {
      "id": "2345740949064245",
      "event_code": "RWT",
      "sent_utc": "2026-02-17T07:42:30+00:00",
      "href": "2345740949064245.json"
    },
    {
      "id": "v2-3.11.25-1333225-1771325692183",
      "event_code": "DMO",
      "sent_utc": "2026-02-17T10:54:53+00:00",
      "href": "v2-3.11.25-1333225-1771325692183.json"
    },
    {
      "id": "PA.000_9031_2026-02-17T07:00:14-05:00",
      "event_code": "RWT",
      "sent_utc": "2026-02-17T12:00:14+00:00",
      "href": "PA.000_9031_2026-02-17T07_00_14-05_00.json"
    },
    {
      "id": "2348077411208973",
      "event_code": "RWT",
      "sent_utc": "2026-02-17T14:13:30+00:00",
      "href": "2348077411208973.json"
    },
    {
      "id": "2355189877051016",
      "event_code": "RWT",
      "sent_utc": "2026-02-17T16:25:25+00:00",
      "href": "2355189877051016.json"
    },
    {
      "id": "17713466910001393177237",
      "event_code": "RWT",
      "sent_utc": "2026-02-17T16:44:51+00:00",
      "href": "17713466910001393177237.json"
    },
    {
      "id": "17713474140001393177238",
      "event_code": "RWT",
      "sent_utc": "2026-02-17T16:56:54+00:00",
      "href": "17713474140001393177238.json"
    },
    {
      "id": "122003576",
      "event_code": "RWT",
      "sent_utc": "2026-02-17T17:11:58+00:00",
      "href": "122003576.json"
    },
    {
      "id": "CAPNET-0-2449-20260217091400",
      "event_code": "RWT",
      "sent_utc": "2026-02-17T17:14:00+00:00",
      "href": "CAPNET-0-2449-20260217091400.json"
    },
    {
      "id": "MI.034_685_2026-02-17T13:19:13-05:00",
      "event_code": "RWT",
      "sent_utc": "2026-02-17T18:19:13+00:00",
      "href": "MI.034_685_2026-02-17T13_19_13-05_00.json"
    },
    {
      "id": "17713540270001393187286",
      "event_code": "ADR",
      "sent_utc": "2026-02-17T18:47:07+00:00",
      "href": "17713540270001393187286.json"
    },
    {
      "id": "2354433962902475",
      "event_code": "RWT",
      "sent_utc": "2026-02-17T19:00:20+00:00",
      "href": "2354433962902475.json"
    },
    {
      "id": "AS-KS-6b93406d-966c-4c5f-9539-dfa82d79ffaf",
      "event_code": "FRW",
      "sent_utc": "2026-02-17T20:43:38+00:00",
      "href": "AS-KS-6b93406d-966c-4c5f-9539-dfa82d79ffaf.json"
    },
    {
      "id": "2351513385045928",
      "event_code": "LAE",
      "sent_utc": "2026-02-17T21:38:40+00:00",
      "href": "2351513385045928.json"
    },
    {
      "id": "2348077411209448",
      "event_code": "EVI",
      "sent_utc": "2026-02-17T21:40:24+00:00",
      "href": "2348077411209448.json"
    },
    {
      "id": "17713674660001393197232",
      "event_code": "RMT",
      "sent_utc": "2026-02-17T22:31:06+00:00",
      "href": "17713674660001393197232.json"
    },
    {
      "id": "6994eced3fedd906b0ac56c5",
      "event_code": "EVI",
      "sent_utc": "2026-02-17T22:46:21+00:00",
      "href": "6994eced3fedd906b0ac56c5.json"
    }
  ]
}