{
  "id": "309104501381185",
  "event_code": "RWT",
  "eas_text": "A civil authority has issued A REQUIRED WEEKLY TEST for the following counties or areas: Milwaukee, WI; at 10:03 AM on FEB 6, 2019 Effective until 11:03 AM. Message from WSLF/CAP.",
  "extra_text": "This is a test message from the Emergency Alert System originating from the Milwaukee County Office of Emergency Management. If this had been an actual emergency, you would have been given official information, news, or instructions. This test is now concluded. SR. This is a test message from the Emergency Alert System originating from the Milwaukee County Office of Emergency Management. If this had been an actual emergency, you would have been given official information, news, or instructions. This test is now concluded. SR.",
  "sent_utc": "2019-02-06T17:03:35+00:00",
  "audio_url": "https://showlowfinityharvester.github.io/ipawscap-archive/alerts/2019/02/06/309104501381185.mp3"
}