{
  "id": "AS-NE-dbe7046f-3a82-491d-b62d-7d9fb6cbc333",
  "event_code": "RWT",
  "eas_text": "A civil authority has issued A REQUIRED WEEKLY TEST for the following counties or areas: Nebraska; at 7:51 AM on APR 30, 2019 Effective until 8:51 AM. Message from WSLF/CAP.",
  "extra_text": "The Nebraska State Patrol has issued a required weekly test of the Emergency Alert System. This is only a test.",
  "sent_utc": "2019-04-30T14:51:55+00:00",
  "audio_url": "https://showlowfinityharvester.github.io/ipawscap-archive/alerts/2019/04/30/AS-NE-dbe7046f-3a82-491d-b62d-7d9fb6cbc333.mp3"
}