{
  "id": "OnSolve-e9cb027872a34e51abe6653e84984e7f",
  "event_code": "RWT",
  "eas_text": "A civil authority has issued A REQUIRED WEEKLY TEST for the following counties or areas: Todd, MN; at 6:43 AM on JUL 24, 2019 Effective until 7:43 AM. Message from WSLF/CAP.",
  "extra_text": "This is a test.  This is the Todd County Required Weekly Test.",
  "sent_utc": "2019-07-24T13:43:57+00:00",
  "audio_url": "https://showlowfinityharvester.github.io/ipawscap-archive/alerts/2019/07/24/OnSolve-e9cb027872a34e51abe6653e84984e7f.mp3"
}