{
  "id": "MI.030_475_2019-03-04T18:09:59-05:00",
  "event_code": "RWT",
  "eas_text": "A civil authority has issued A REQUIRED WEEKLY TEST for the following counties or areas: Allegan, MI; at 4:09 PM on MAR 4, 2019 Effective until 4:24 PM. Message from WSLF/CAP.",
  "extra_text": "THIS IS A REQUIRED WEEKLY TEST OF THE EMERGENCY ALERT SYSTEM FOR ALLEGAN COUNTY. THIS IS ONLY A TEST.",
  "sent_utc": "2019-03-04T23:09:59+00:00",
  "audio_url": "https://showlowfinityharvester.github.io/ipawscap-archive/alerts/2019/03/04/MI.030_475_2019-03-04T18_09_59-05_00.mp3"
}