{
  "alerts": [
    {
      "id": "CAPNET-0-3438-20260515102300",
      "event_code": "RWT",
      "sent_utc": "2026-05-15T15:23:00+00:00",
      "href": "CAPNET-0-3438-20260515102300.json"
    },
    {
      "id": "OnSolve-216ece0ae53c446fba845d979078ac98",
      "event_code": "RWT",
      "sent_utc": "2026-05-15T16:14:00+00:00",
      "href": "OnSolve-216ece0ae53c446fba845d979078ac98.json"
    },
    {
      "id": "2507609676450630",
      "event_code": "FRW",
      "sent_utc": "2026-05-15T18:53:35+00:00",
      "href": "2507609676450630.json"
    },
    {
      "id": "2507609676450636",
      "event_code": "FRW",
      "sent_utc": "2026-05-15T18:56:55+00:00",
      "href": "2507609676450636.json"
    },
    {
      "id": "2507609676450639",
      "event_code": "FRW",
      "sent_utc": "2026-05-15T18:59:25+00:00",
      "href": "2507609676450639.json"
    },
    {
      "id": "2507815834880988",
      "event_code": "EVI",
      "sent_utc": "2026-05-15T19:36:35+00:00",
      "href": "2507815834880988.json"
    },
    {
      "id": "WENS_IPAWS_CONNECT22026415153815",
      "event_code": "FRW",
      "sent_utc": "2026-05-15T19:38:15+00:00",
      "href": "WENS_IPAWS_CONNECT22026415153815.json"
    },
    {
      "id": "2507815834881000",
      "event_code": "EVI",
      "sent_utc": "2026-05-15T19:46:35+00:00",
      "href": "2507815834881000.json"
    },
    {
      "id": "2507815834881023",
      "event_code": "EVI",
      "sent_utc": "2026-05-15T20:06:00+00:00",
      "href": "2507815834881023.json"
    },
    {
      "id": "WENS_IPAWS_CONNECT22026415184058",
      "event_code": "FRW",
      "sent_utc": "2026-05-15T22:40:58+00:00",
      "href": "WENS_IPAWS_CONNECT22026415184058.json"
    },
    {
      "id": "2507815834881163",
      "event_code": "EVI",
      "sent_utc": "2026-05-15T22:56:45+00:00",
      "href": "2507815834881163.json"
    },
    {
      "id": "2507815834881333",
      "event_code": "LAE",
      "sent_utc": "2026-05-16T02:21:51+00:00",
      "href": "2507815834881333.json"
    }
  ]
}