{
  "id": "AS-NV-227b3204-b819-4501-8fcb-9094265ef7b5",
  "event_code": "RWT",
  "eas_text": "A civil authority has issued A REQUIRED WEEKLY TEST for the following counties or areas: Alpine, CA; at 9:44 AM on OCT 2, 2019 Effective until 9:59 AM. Message from WSLF/CAP.",
  "extra_text": "Douglas County authorities have issued a required weekly test for Alpine County CA.  This is only a test. No action required.",
  "sent_utc": "2019-10-02T16:44:37+00:00",
  "audio_url": "https://showlowfinityharvester.github.io/ipawscap-archive/alerts/2019/10/02/AS-NV-227b3204-b819-4501-8fcb-9094265ef7b5.mp3"
}