{
  "id": "AS-NV-08d0bb62-3193-45e1-b253-db29845fdc04",
  "event_code": "RWT",
  "eas_text": "A civil authority has issued A REQUIRED WEEKLY TEST for the following counties or areas: Esmeralda; Lincoln; Nye; White Pine; Clark, NV; at 3:15 AM on SEP 30, 2019 Effective until 4:15 AM. Message from WSLF/CAP.",
  "extra_text": "REQUIRED WEEKLY TEST REQUIRED WEEKLY TEST",
  "sent_utc": "2019-09-30T10:15:16+00:00",
  "audio_url": "https://showlowfinityharvester.github.io/ipawscap-archive/alerts/2019/09/30/AS-NV-08d0bb62-3193-45e1-b253-db29845fdc04.mp3"
}