{
  "alerts": [
    {
      "id": "2351513385043993",
      "event_code": "RWT",
      "sent_utc": "2026-02-15T12:06:00+00:00",
      "href": "2351513385043993.json"
    },
    {
      "id": "2355189877049297",
      "event_code": "RWT",
      "sent_utc": "2026-02-15T16:01:55+00:00",
      "href": "2355189877049297.json"
    },
    {
      "id": "17711960370001393187239",
      "event_code": "ADR",
      "sent_utc": "2026-02-15T22:53:57+00:00",
      "href": "17711960370001393187239.json"
    },
    {
      "id": "RWT_GDT_1771203600000",
      "event_code": "RWT",
      "sent_utc": "2026-02-16T01:00:00+00:00",
      "href": "RWT_GDT_1771203600000.json"
    },
    {
      "id": "2355189877049629",
      "event_code": "RWT",
      "sent_utc": "2026-02-16T02:10:40+00:00",
      "href": "2355189877049629.json"
    },
    {
      "id": "17712139820001393177196",
      "event_code": "ADR",
      "sent_utc": "2026-02-16T03:53:02+00:00",
      "href": "17712139820001393177196.json"
    }
  ]
}