{
  "alerts": [
    {
      "id": "CAPNET-0-5234-20190928122000",
      "event_code": "RWT",
      "sent_utc": "2019-09-28T16:20:00+00:00",
      "href": "CAPNET-0-5234-20190928122000.json"
    },
    {
      "id": "OnSolve-bbd228a7745e4ae2881d991ace07cd27",
      "event_code": "RWT",
      "sent_utc": "2019-09-29T01:39:05+00:00",
      "href": "OnSolve-bbd228a7745e4ae2881d991ace07cd27.json"
    },
    {
      "id": "CAPNET-0-4749-20190928235200",
      "event_code": "RWT",
      "sent_utc": "2019-09-29T03:52:00+00:00",
      "href": "CAPNET-0-4749-20190928235200.json"
    }
  ]
}