{
  "id": "AS-NV-d926e885-7660-40dc-90e3-a033ac811099",
  "event_code": "RWT",
  "eas_text": "A civil authority has issued A REQUIRED WEEKLY TEST for the following counties or areas: Eureka; Humboldt; Lander; Lyon; Mineral; Pershing; Storey; Washoe; Carson City; Elko; Douglas; Churchill, NV; at 7:55 AM on AUG 8, 2019 Effective until 8:55 AM. Message from WSLF/CAP.",
  "extra_text": "REQUIRED WEEKLY TEST REQUIRED WEEKLY TEST",
  "sent_utc": "2019-08-08T14:55:20+00:00",
  "audio_url": "https://showlowfinityharvester.github.io/ipawscap-archive/alerts/2019/08/08/AS-NV-d926e885-7660-40dc-90e3-a033ac811099.mp3"
}